{
  "project_info": {
    "project_number": "298519303258",
    "project_id": "fir-demo-dac55",
    "storage_bucket": "fir-demo-dac55.appspot.com"
  },
  "client": [
    {
      "client_info": {
        "mobilesdk_app_id": "1:298519303258:android:b46415ad36649400f53463",
        "android_client_info": {
          "package_name": "com.example.firebaseapplication"
        }
      },
      "oauth_client": [
        {
          "client_id": "298519303258-lcq2k4qs4vldvbr2mfjkm1ku434q8oh8.apps.googleusercontent.com",
          "client_type": 3
        }
      ],
      "api_key": [
        {
          "current_key": "AIzaSyCtxe5BJ2coccxBkD63G7otV_PwUomc21M"
        }
      ],
      "services": {
        "appinvite_service": {
          "other_platform_oauth_client": [
            {
              "client_id": "298519303258-lcq2k4qs4vldvbr2mfjkm1ku434q8oh8.apps.googleusercontent.com",
              "client_type": 3
            }
          ]
        }
      }
    }
  ],
  "configuration_version": "1"
}